Workbook

Sheet 9月サマリー
B2: 9月 実績振り返り｜コーデ+TREEBATON ＋ 建築 ＋ OEM
B3: ★コーデTB_実績(4月-前月)_26年度（2026-10-06 19:38 出力・117件） ／ 単位：千円 ／ 完了予定日ベース・フェーズ07.成約・失注除外 ／ 8月末 → 9月末 の差分＝9月の実績
B5: ① 実績サマリー（8月末 → 9月末）
B6: 累計実績の差が9月の成果です。
B7: 8月末 累計 | E7: 9月末 累計 | H7: 9月の実績 | K7: 累計の伸び率
B8: =SUM(月別推移!$C$4:$C$9)-INDEX(月別推移!$C$4:$C$9,6) -> 84199 | E8: =SUM(月別推移!$C$4:$C$9) -> 105243 | H8: =INDEX(月別推移!$C$4:$C$9,6) -> 21044 | K8: =INDEX(月別推移!$C$4:$C$9,6)/(SUM(月別推移!$C$4:$C$9)-INDEX(月別推移!$C$4:$C$9,6)) -> 0.24993171
B9: 4月〜8月 98件 | E9: 4月〜9月 117件 | H9: 8月末からの増加分 | K9: 8月末累計に対して
B11: 9月の中身
B12: 件数 | E12: 平均単価 | H12: 粗利 | K12: 粗利率
B13: =INDEX(月別推移!$B$4:$B$9,6) -> 19 | E13: =INDEX(月別推移!$C$4:$C$9,6)/INDEX(月別推移!$B$4:$B$9,6) -> 1107.5789 | H13: =INDEX(月別推移!$D$4:$D$9,6) -> 5665 | K13: =INDEX(月別推移!$D$4:$D$9,6)/INDEX(月別推移!$C$4:$C$9,6) -> 0.26919787
B14: 8月は13件 | E14: 8月は328 | H14: 8月は2,303 | K14: 8月は54.0%・上期平均41.4%
B31: 8月 4,265 → 9月 21,044。金額は 4.9倍 に伸びました。上期6ヶ月で2番目に大きい月です。
B32: 一方で粗利率は 26.9%。8月の54.0%、上期平均41.4%を下回り、上期では4月・6月に次いで低い水準です。
B34: ② 9月の実績｜誰が作ったか
B35: 商談所有者別。上位3名で全体の95.6%です。
B36: 片岡さん | E36: 安達さん | H36: 落合さん | K36: その他3名
B37: =SUMIF('9月 実績明細'!$F$4:$F$22,"片岡 雅貴",'9月 実績明細'!$C$4:$C$22) -> 9006 | E37: =SUMIF('9月 実績明細'!$F$4:$F$22,"安達 芳樹",'9月 実績明細'!$C$4:$C$22) -> 6334 | H37: =SUMIF('9月 実績明細'!$F$4:$F$22,"落合 あゆみ",'9月 実績明細'!$C$4:$C$22) -> 4774 | K37: =グラフ用データ!B16 -> 928
B38: 6件・全体の42.8% | E38: 3件・全体の30.1%（全部ホウライ） | H38: 4件・全体の22.7% | K38: 恒冨・五江渕・森口 計6件
B55: 片岡さんの6件のうち乃村工藝社が4件・8,783（全体の41.7%）。1社への依存が続いています。
B57: ③ 9月の実績｜どこから来たか
B58: 商談のきっかけ別。リピート系が73.8%を占めます。
B59: 当社/営業G(リピート) | E59: 顧客/取引先リピート | H59: 当社/商談前営業 | K59: その他
B60: =SUMIF('9月 実績明細'!$G$4:$G$22,"当社/営業G(リピート)",'9月 実績明細'!$C$4:$C$22) -> 9085 | E60: =SUMIF('9月 実績明細'!$G$4:$G$22,"顧客/取引先リピート",'9月 実績明細'!$C$4:$C$22) -> 6443 | H60: =SUMIF('9月 実績明細'!$G$4:$G$22,"当社/商談前営業",'9月 実績明細'!$C$4:$C$22) -> 4950 | K60: =グラフ用データ!B22 -> 564
B61: 4件・43.2% | E61: 8件・30.6% | H61: 2件・23.5%（どちらもホウライ） | K61: 追加受注・新規・eTREE 計5件
B78: 商談前営業が4,950（23.5%）。ただし2件ともホウライ様の千本松牧場PJで、実質1社です。
B79: 新規開拓（営業G新規）は1件38、eTREE経由は1件12。新しい入口からの実績はほぼありません。
B81: ④ 今月のトピック
B82: 各トピックを9月の実績（成約金額）と突き合わせています。
B83: トピック | D83: 何があったか | G83: 9月の実績への寄与 | J83: 補足
B84: リリカラさん | D84: コンペ対応が完了。 | G84: このレポートに該当なし（9月実績19件に含まれない） | J84: 受注なら10月以降の実績に乗る。結果にかかわらずSFに起票を
B85: ATONA（乃村工藝社） | D85: 京都案件の納品・売上計上が完了。FFEと内装突板の2件。 | G85: 8,480（FFE 5,900＋内装突板 2,580）＝9月実績の40.3%。粗利 2,070・粗利率24.4% | J85: 9月で最大の実績。きっかけは「営業G(リピート)」。所有者は片岡さん
B86: ホウライさん | D86: 千本松牧場PJの3件が成約。林内ベンチは追加依頼も入った。 | G86: 6,334（④小サイン・林内ベンチ 3,000／⑤記念品 1,950／ホウライ様予算ベンチ 1,384）＝30.1%。粗利 1,948・粗利率30.8% | J86: うち2件（4,950）が「商談前営業」。9月の商談前営業の実績はすべてここ。所有者は安達さん
B87: 素朴屋さん | D87: 年内の納品スケジュールが固まった。認証桧柾目材供給PJの2回目を計上。 | G87: 3,000（2回目 SGEC富士市）＝14.3%。粗利 580・粗利率19.3% | J87: 1回目は6月に8,095を計上済み。上期で2件・11,095。所有者は落合さん
B88: CUEさん | D88: イベント什器を9/30に成約。 | G88: 1,475＝7.0%。粗利 459・粗利率31.1% | J88: きっかけは「取引先リピート」。所有者は落合さん
B89: 内閣府 檜板 | D89: 9/28に成約。取引先は株式会社ゼロワン。 | G89: 149＝0.7%。粗利 56・粗利率37.6% | J89: 金額は小さいが実績として使える。同種案件の横展開先を探す
B91: ATONA・ホウライ・素朴屋・CUE・内閣府の5件で9月実績の92.4%（19,438／21,044）。残り14件は合計1,606です。
B92: リリカラさんのコンペはこのレポートに実績として出てきません。結果にかかわらずSFに起票しないと、動いた事実が数字に残りません。

Sheet Sheet

Sheet 9月 実績明細
A1: 9月の成約実績（19件）
A2: 完了予定日が2026/09/01〜09/30、フェーズ07.成約。単位：千円。
A3: 取引先 | B3: 商談名 | C3: 金額 | D3: 粗利 | E3: 粗利率 | F3: 商談所有者 | G3: 商談のきっかけ | H3: レコードタイプ
A4: 株式会社乃村工藝社 | B4: ATONA_京都_FFE | C4: 5900 | D4: 1490 | E4: 0.25254237 | F4: 片岡 雅貴 | G4: 当社/営業G(リピート) | H4: 木材コーディネート
A5: 素朴屋株式会社 | B5: 子商談_認証桧柾目材供給PJ_2回目(SGEC富士市) | C5: 3000 | D5: 580 | E5: 0.19347333 | F5: 落合 あゆみ | G5: 顧客/取引先リピート | H5: 木材コーディネート
A6: ホウライ株式会社 | B6: 26年度_千本松牧場PJ_④小サイン・林内ベンチ製造 | C6: 3000 | D6: 585 | E6: 0.19486667 | F6: 安達 芳樹 | G6: 当社/商談前営業 | H6: 木材コーディネート
A7: 株式会社乃村工藝社 | B7: ATONA_京都_内装突板 | C7: 2580 | D7: 580 | E7: 0.2248062 | F7: 片岡 雅貴 | G7: 当社/営業G(リピート) | H7: 木材コーディネート
A8: ホウライ株式会社 | B8: 26年度_千本松牧場PJ_⑤記念品製造／バードコール＆写真フレーム | C8: 1950 | D8: 947 | E8: 0.4854159 | F8: 安達 芳樹 | G8: 当社/商談前営業 | H8: 木材コーディネート
A9: CUE株式会社 | B9: イベント什器製作 | C9: 1475 | D9: 459 | E9: 0.31118644 | F9: 落合 あゆみ | G9: 顧客/取引先リピート | H9: 木材コーディネート
A10: ホウライ株式会社 | B10: ホウライ様予算_26年度_千本松牧場PJ_林内ベンチ製造 | C10: 1384 | D10: 416 | E10: 0.30078012 | F10: 安達 芳樹 | G10: 顧客/取引先リピート | H10: 木材コーディネート
A11: 株式会社ADX | B11: CLT試験材 | C11: 535 | D11: 125 | E11: 0.2332 | F11: 恒冨 春香 | G11: 当社/営業G(リピート) | H11: 建築案件
A12: 株式会社乃村工藝社 | B12: HOTEL THE MITSUI_補修_9月 | C12: 265 | D12: 65 | E12: 0.24528302 | F12: 片岡 雅貴 | G12: 追加受注 | H12: 木材コーディネート
A13: 株式会社アースボート | B13: アースボートVer.3行先未定（本体棟6台＋寝室棟４台）②（9月度） | C13: 187 | D13: 187 | E13: 1 | F13: 恒冨 春香 | G13: その他 | H13: OEM
A14: ラルフローレン合同会社 | B14: 水戸京成RLC | C14: 173 | D14: 31 | E14: 0.17663972 | F14: 片岡 雅貴 | G14: 顧客/取引先リピート | H14: 木材コーディネート
A15: 株式会社丹青社 | B15: ロイヤルHD本社工場直販店(福岡)_既存樹活用（引上げ・製材・乾燥） | C15: 150 | D15: 72 | E15: 0.47866667 | F15: 落合 あゆみ | G15: 顧客/取引先リピート | H15: 木材コーディネート
... A22: 株式会社プレイブ | B22: 藍建材サンプル | C22: 12 | D22: 0 | E22: 0.019417476 | F22: 森口 大世 | G22: 顧客/eTREE・入電 | H22: 木材コーディネート

Sheet 月別推移
A1: 月別の成約実績（26年度 上期）
A2: 完了予定日ベース。フェーズ07.成約・失注除外。単位：千円。
A3: 月 | B3: 件数 | C3: 金額 | D3: 粗利 | E3: 粗利率 | F3: 平均単価
A4: 2026年04月 | B4: 12 | C4: 13688 | D4: 1820 | E4: 0.13299611 | F4: 1141
A5: 2026年05月 | B5: 30 | C5: 29952 | D5: 21720 | E5: 0.72516079 | F5: 998
A6: 2026年06月 | B6: 29 | C6: 21170 | D6: 3886 | E6: 0.18355641 | F6: 730
A7: 2026年07月 | B7: 14 | C7: 15124 | D7: 8183 | E7: 0.54102931 | F7: 1080
A8: 2026年08月 | B8: 13 | C8: 4265 | D8: 2303 | E8: 0.54007861 | F8: 328
A9: 2026年09月 | B9: 19 | C9: 21044 | D9: 5665 | E9: 0.26919847 | F9: 1108

Sheet 上期 実績明細
A1: 26年度 上期の成約実績（117件）
A2: 完了予定日が2026/04/01〜09/30、フェーズ07.成約。単位：千円。
A3: 完了予定月 | B3: 取引先 | C3: 商談名 | D3: 金額 | E3: 粗利 | F3: 商談所有者 | G3: 商談のきっかけ | H3: レコードタイプ
A4: 2026/04 | B4: 株式会社アースボート | C4: アースボートVer.2.0.6（上田、2026年4月分3台） | D4: 7425 | E4: 675 | F4: 恒冨 春香 | G4: その他 | H4: OEM
A5: 2026/04 | B5: 株式会社アースボート | C5: アースボートVer2.0.6（上田、2026年4月分3台）② | D5: 2475 | E5: 230 | F5: 恒冨 春香 | G5: その他 | H5: OEM
A6: 2026/04 | B6: 株式会社VIE | C6: リゾナーレ八ヶ岳プロジェクト | D6: 870 | E6: 118 | F6: 片岡 雅貴 | G6: 顧客/eTREE・入電 | H6: 木材コーディネート
A7: 2026/04 | B7: 有限会社サード･ワン | C7: 白樺丸太 | D7: 832 | E7: 170 | F7: 安達 芳樹 | G7: 顧客/eTREE・入電 | H7: 木材コーディネート
A8: 2026/04 | B8: 株式会社スペース | C8: スターバックス_TXアベニューつくば店 | D8: 680 | E8: 107 | F8: 五江渕啓太 | G8: 当社/営業G(新規) | H8: 木材コーディネート
A9: 2026/04 | B9: 三井デザインテック株式会社 | C9: 上用賀五丁目PJ_モデルルーム(モックアップ)_玄関土間プラン | D9: 532 | E9: 99 | F9: 五江渕啓太 | G9: 顧客/取引先リピート | H9: 木材コーディネート
A10: 2026/04 | B10: 株式会社パーク・コーポレーション | C10: （仮称）クリオ石神井公園_保管･天然乾燥 | D10: 384 | E10: 250 | F10: 片岡 雅貴 | G10: 顧客/取引先リピート | H10: TREEBATON
A11: 2026/04 | B11: 遼有堂 | C11: レッドシダー特注材 | D11: 137 | E11: 21 | F11: 恒冨 春香 | G11: 顧客/取引先リピート | H11: 木材コーディネート
A12: 2026/04 | B12: 遼有堂 | C12: サワラ桶材料 | D12: 132 | E12: 30 | F12: 恒冨 春香 | G12: 顧客/取引先リピート | H12: 木材コーディネート
A13: 2026/04 | B13: 遼有堂 | C13: 杉幅広板 | D13: 126 | E13: 26 | F13: 恒冨 春香 | G13: 顧客/取引先リピート | H13: 木材コーディネート
A14: 2026/04 | B14: 株式会社アースボート | C14: アースボートVer3.0.4（北軽井沢、MOCver、2026年3月分）② | D14: 92 | E14: 92 | F14: 恒冨 春香 | G14: その他 | H14: OEM
A15: 2026/04 | B15: 三井デザインテック株式会社 | C15: サンプル用_NEC本社改修_ギャザリングエリアMokkun | D15: 4 | E15: 4 | F15: 五江渕啓太 | G15: その他 | H15: 木材コーディネート
... A120: 2026/09 | B120: 株式会社プレイブ | C120: 藍建材サンプル | D120: 12 | E120: 0 | F120: 森口 大世 | G120: 顧客/eTREE・入電 | H120: 木材コーディネート

Sheet グラフ用データ
A1: グラフ用データ（サマリーのグラフが参照します）
A2: すべて明細シートからの自動計算。単位：千円。
A4: 月 | B4: 金額 | C4: 粗利
A5: 2026年04月 | B5: =月別推移!C4 -> 13688 | C5: =月別推移!D4 -> 1820
A6: 2026年05月 | B6: =月別推移!C5 -> 29952 | C6: =月別推移!D5 -> 21720
A7: 2026年06月 | B7: =月別推移!C6 -> 21170 | C7: =月別推移!D6 -> 3886
A8: 2026年07月 | B8: =月別推移!C7 -> 15124 | C8: =月別推移!D7 -> 8183
A9: 2026年08月 | B9: =月別推移!C8 -> 4265 | C9: =月別推移!D8 -> 2303
A10: 2026年09月 | B10: =月別推移!C9 -> 21044 | C10: =月別推移!D9 -> 5665
A12: 9月 商談所有者別
A13: 片岡 雅貴 | B13: =SUMIF('9月 実績明細'!$F$4:$F$22,"片岡 雅貴",'9月 実績明細'!$C$4:$C$22) -> 9006
A14: 安達 芳樹 | B14: =SUMIF('9月 実績明細'!$F$4:$F$22,"安達 芳樹",'9月 実績明細'!$C$4:$C$22) -> 6334
A15: 落合 あゆみ | B15: =SUMIF('9月 実績明細'!$F$4:$F$22,"落合 あゆみ",'9月 実績明細'!$C$4:$C$22) -> 4774
A16: その他（恒冨・五江渕・森口） | B16: =SUM('9月 実績明細'!$C$4:$C$22)-SUM(B13:B15) -> 928
A18: 9月 商談のきっかけ別
A19: 当社/営業G(リピート) | B19: =SUMIF('9月 実績明細'!$G$4:$G$22,"当社/営業G(リピート)",'9月 実績明細'!$C$4:$C$22) -> 9085
A20: 顧客/取引先リピート | B20: =SUMIF('9月 実績明細'!$G$4:$G$22,"顧客/取引先リピート",'9月 実績明細'!$C$4:$C$22) -> 6443
A21: 当社/商談前営業 | B21: =SUMIF('9月 実績明細'!$G$4:$G$22,"当社/商談前営業",'9月 実績明細'!$C$4:$C$22) -> 4950
A22: その他（追加受注・新規・eTREE 他） | B22: =SUM('9月 実績明細'!$C$4:$C$22)-SUM(B19:B21) -> 564

Sheet 算出方法
A1: 算出方法と注意点
A3: ■ 使用データ
A4: レポート名 | B4: ★コーデTB_実績(4月-前月)_26年度
A5: 出力日時 | B5: 2026-10-06 19:38:40
A6: 件数 | B6: 117件・合計 105,242,696円
A7: 抽出条件 | B7: 完了予定日 2026/04/01〜2027/03/31 かつ 完了予定日＜今月（＝9/30まで）
A8: レコードタイプ | B8: 木材コーディネート／TREEBATON／建築案件／OEM
A9: 除外 | B9: フェーズ00_失注、テスト商談、＊原価管理用＊
A11: ■ 期間の取り方
A12: 8月末 累計 | B12: 完了予定月が4月〜8月の合計（98件 84,199千円）
A13: 9月末 累計 | B13: 完了予定月が4月〜9月の合計（117件 105,243千円）
A14: 9月の実績 | B14: 9月末累計 − 8月末累計 ＝ 完了予定月が9月の合計（19件 21,044千円）
A16: ■ 前回版との違い
A17: データの性質 | B17: このレポートは全117件が確度A・フェーズ07.成約の「実績」のみ。AB玉・CD玉の区分がありません
A18: 構成の変更 | B18: 前回の②AB玉／③CD玉に代えて、②商談所有者別／③商談のきっかけ別 としています
A19: 対象の違い | B19: OEM（1件 187千円）が含まれます。前回の玉ベース版はコーデTB＋建築のみでした
A21: ■ 注意点
A22: 粗利率 | B22: 9月は26.9%。上期平均41.4%、8月54.0%を下回る
A23: 集中度 | B23: ATONA・ホウライ・素朴屋・CUE・内閣府の5件で9月実績の92.4%
A24: 取引先の偏り | B24: 乃村工藝社4件 8,783 で全体の41.7%
A25: 所有者の偏り | B25: 片岡・安達・落合の3名で95.6%
A26: 新規の入口 | B26: 営業G(新規)1件 38千円、eTREE経由1件 12千円。新しい入口からの実績はほぼゼロ
A27: リリカラ | B27: このレポートに該当なし。SFに商談が登録されていない可能性がある
